jsonize_db
