Metadata-Version: 1.0
Name: jsonize-db
Version: 0.2.0
Summary: Loading and unloading DB to JSONs
Home-page: UNKNOWN
Author: UNKNOWN
Author-email: c-mao@mail.ru
License: UNKNOWN
Platform: UNKNOWN
